wxtools/__init__.py
wxtools/cv/__init__.py
wxtools/cv/bin2png.py
wxtools/cv/img_quality.py
wxtools/cv/img_utils.py
wxtools/io_utils/__init__.py
wxtools/io_utils/io_utils.py
wxtools/linalg/__init__.py
wxtools/linalg/similarity.py
wxtools/logger/__init__.py
wxtools/logger/logger.py
wxtools/logger/utils.py
wxtools/test/__init__.py
wxtools/utils/AverageMeter.py
wxtools/utils/__init__.py
wxtools/utils/grad_cam.py
wxtools/utils/mlpro_utils.py
wxtools/utils/timer.py
wxtools-0.2.6.1.dist-info/LICENSE
wxtools-0.2.6.1.dist-info/METADATA
wxtools-0.2.6.1.dist-info/WHEEL
wxtools-0.2.6.1.dist-info/top_level.txt
wxtools-0.2.6.1.dist-info/RECORD
