Metadata-Version: 2.1
Name: wxtools
Version: 0.2.6.1
License-File: LICENSE
Requires-Dist: onnxruntime >=1.12.1
Requires-Dist: numpy >=1.23.0
Requires-Dist: opencv-python >=4.5.2.54
Requires-Dist: tqdm >=4.65.2
Requires-Dist: setuptools >=60.2.0
